pymockache/__init__.py
pymockache/async_/__init__.py
pymockache/async_/decorators.py
pymockache/async_/backends/__init__.py
pymockache/async_/backends/abstract.py
pymockache/async_/backends/redis.py
pymockache-0.0.2.dist-info/METADATA
pymockache-0.0.2.dist-info/WHEEL
pymockache-0.0.2.dist-info/top_level.txt
pymockache-0.0.2.dist-info/RECORD
