Metadata-Version: 2.1
Name: pymockache
Version: 0.0.2
Summary: Caching for separated functions
Home-page: UNKNOWN
Author-email: kirill.s.job@gmail.com
License: UNKNOWN
Platform: UNKNOWN
Classifier: Programming Language :: Python :: 3.7
Requires-Python: >=3.7
Requires-Dist: aioredis (>=1.3.1)
